<?xml version="1.0" encoding="utf-8"?>
<LanguageData>

  <BRF_CrimsonButcher.label>緋紅屠殺者</BRF_CrimsonButcher.label>
  <BRF_CrimsonButcher.description>活體合金刀刃上攜帶生物病毒可以令敵人皮開肉綻。這把有生命的屠刀渴望著殺戮。</BRF_CrimsonButcher.description>
  <BRF_CrimsonButcher.tools.handle.label>握柄</BRF_CrimsonButcher.tools.handle.label>
  <BRF_CrimsonButcher.tools.point.label>刀尖</BRF_CrimsonButcher.tools.point.label>
  <BRF_CrimsonButcher.tools.edge.label>刀刃</BRF_CrimsonButcher.tools.edge.label>

  <BRF_CrimsonDecimator.label>緋紅斬首者</BRF_CrimsonDecimator.label>
  <BRF_CrimsonDecimator.description>活體合金刀刃上攜帶生物病毒可以令敵人皮開肉綻。T這把會呼吸的斧頭的唯一使命就是破門而入，砍下某人的腦袋。</BRF_CrimsonDecimator.description>
  <BRF_CrimsonDecimator.tools.handle.label>握柄</BRF_CrimsonDecimator.tools.handle.label>
  <BRF_CrimsonDecimator.tools.edge.label>斧刃</BRF_CrimsonDecimator.tools.edge.label>


</LanguageData>